add2anki/__init__.py
add2anki/anki_client.py
add2anki/audio.py
add2anki/cli.py
add2anki/config.py
add2anki/exceptions.py
add2anki/language_detection.py
add2anki/srt.py
add2anki/translation.py
add2anki-0.1.2.dist-info/METADATA
add2anki-0.1.2.dist-info/WHEEL
add2anki-0.1.2.dist-info/entry_points.txt
add2anki-0.1.2.dist-info/licenses/LICENSE
add2anki-0.1.2.dist-info/RECORD
