Metadata-Version: 2.4
Name: add2anki
Version: 0.1.2
Summary: CLI tool to add language learning cards to Anki
Project-URL: Homepage, https://github.com/osteele/add2anki
Project-URL: Documentation, https://osteele.github.io/add2anki/
Project-URL: Issues, https://github.com/osteele/add2anki/issues
Project-URL: Source, https://github.com/osteele/add2anki
Author-email: Oliver Steele <steele@osteele.com>
License-Expression: MIT
License-File: LICENSE
Requires-Python: >=3.11
Requires-Dist: click>=8.1.7
Requires-Dist: contextual-langdetect==0.1.1
Requires-Dist: elevenlabs>=0.2.26
Requires-Dist: fast-langdetect>=0.3.1
Requires-Dist: openai>=1.68.2
Requires-Dist: pydantic>=2.10.6
Requires-Dist: requests>=2.31.0
Requires-Dist: rich>=13.7.0
